
            {
                "id":"m74",
                "titulo":"Juízo Final",
                "tipo":""
                
                    ,"compositor":"Camillo de Nardis"
                
                    ,"compositor":"Franco Cesarini"
                
                    ,"instrumentos": [
                        
                            {
                                "designação":"",
                                
                                    "voz":"I",
                                
                                "path":"JuizoFinal-clarinete1.pdf"
                            }
                            ,
                            {
                                "designação":"",
                                
                                    "voz":"II",
                                
                                "path":"JuizoFinal-clarinete2.pdf"
                            }
                            ,
                            {
                                "designação":"",
                                
                                    "voz":"III",
                                
                                "path":"JuizoFinal-clarinete3.pdf"
                            }
                            ,
                            {
                                "designação":"",
                                
                                "path":"JuizoFinal-eufonio.pdf"
                            }
                            ,
                            {
                                "designação":"",
                                
                                    "voz":"II",
                                
                                "path":"JuizoFinal-fagote2.pdf"
                            }
                            ,
                            {
                                "designação":"",
                                
                                    "voz":"I",
                                
                                "path":"JuizoFinal-flauta1.pdf"
                            }
                            ,
                            {
                                "designação":"",
                                
                                    "voz":"II",
                                
                                "path":"JuizoFinal-flauta2.pdf"
                            }
                            ,
                            {
                                "designação":"",
                                
                                    "voz":"I",
                                
                                "path":"JuizoFinal-percussao1.pdf"
                            }
                            ,
                            {
                                "designação":"",
                                
                                    "voz":"II",
                                
                                "path":"JuizoFinal-percussao2.pdf"
                            }
                            ,
                            {
                                "designação":"",
                                
                                    "voz":"II",
                                
                                "path":"JuizoFinal-saxA2.pdf"
                            }
                            ,
                            {
                                "designação":"",
                                
                                "path":"JuizoFinal-saxB.pdf"
                            }
                            ,
                            {
                                "designação":"",
                                
                                "path":"JuizoFinal-saxT.pdf"
                            }
                            ,
                            {
                                "designação":"",
                                
                                "path":"JuizoFinal-timpanos.pdf"
                            }
                            ,
                            {
                                "designação":"",
                                
                                    "voz":"I",
                                
                                "path":"JuizoFinal-trombone1.pdf"
                            }
                            ,
                            {
                                "designação":"",
                                
                                    "voz":"II",
                                
                                "path":"JuizoFinal-trombone2.pdf"
                            }
                            ,
                            {
                                "designação":"",
                                
                                    "voz":"III",
                                
                                "path":"JuizoFinal-trombone3.pdf"
                            }
                            ,
                            {
                                "designação":"",
                                
                                    "voz":"I",
                                
                                "path":"JuizoFinal-trompete1.pdf"
                            }
                            ,
                            {
                                "designação":"",
                                
                                    "voz":"II",
                                
                                "path":"JuizoFinal-trompete2.pdf"
                            }
                            ,
                            {
                                "designação":"",
                                
                                    "voz":"III",
                                
                                "path":"JuizoFinal-trompete3.pdf"
                            }
                            ,
                            {
                                "designação":"",
                                
                                "path":"JuizoFinal-tuba.pdf"
                            }
                            
                    ]
                
            }
        